README.md
setup.cfg
setup.py
explainerdashboard/__init__.py
explainerdashboard/cli.py
explainerdashboard/custom.py
explainerdashboard/dashboard_methods.py
explainerdashboard/dashboard_tabs.py
explainerdashboard/dashboards.py
explainerdashboard/datasets.py
explainerdashboard/explainer_methods.py
explainerdashboard/explainer_plots.py
explainerdashboard/explainers.py
explainerdashboard/assets/bootstrap.min.css
explainerdashboard/assets/favicon.ico
explainerdashboard/dashboard_components/__init__.py
explainerdashboard/dashboard_components/classifier_components.py
explainerdashboard/dashboard_components/composites.py
explainerdashboard/dashboard_components/connectors.py
explainerdashboard/dashboard_components/decisiontree_components.py
explainerdashboard/dashboard_components/overview_components.py
explainerdashboard/dashboard_components/regression_components.py
explainerdashboard/dashboard_components/shap_components.py
explainerdashboard/datasets/titanic_test.csv
explainerdashboard/datasets/titanic_train.csv
explainerdashboard/static/bootstrap.min.css
explainerdashboard/static/bootstrap.min.js
explainerdashboard/static/favicon.ico
explainerdashboard/static/jquery-3.5.1.slim.min.js
fwexplainerdashboard.egg-info/PKG-INFO
fwexplainerdashboard.egg-info/SOURCES.txt
fwexplainerdashboard.egg-info/dependency_links.txt
fwexplainerdashboard.egg-info/entry_points.txt
fwexplainerdashboard.egg-info/requires.txt
fwexplainerdashboard.egg-info/top_level.txt
tests/__init__.py
tests/test_boosting_models.py
tests/test_cats_only.py
tests/test_classifier_base.py
tests/test_classifier_explainer.py
tests/test_cli.py
tests/test_cv.py
tests/test_dashboard.py
tests/test_decisiontrees.py
tests/test_externalsource.py
tests/test_linear_model.py
tests/test_multiclass.py
tests/test_njobs.py
tests/test_pipelines.py
tests/test_randomforest_explainer.py
tests/test_regression_base.py
tests/test_regression_explainer.py
tests/test_skorch_models.py
tests/test_xgboost_explainer.py