Metadata-Version: 1.2
Name: fwexplainerdashboard
Version: 0.3.6
Summary: Quickly build Explainable AI dashboards that show the inner workings of so-called "blackbox" machine learning models.
Home-page: https://github.com/oegedijk/explainerdashboard
Author: Oege Dijk
Author-email: oegedijk@gmail.com
License: MIT
Project-URL: Github page, https://github.com/oegedijk/explainerdashboard/
Project-URL: Documentation, https://explainerdashboard.readthedocs.io/
Keywords: machine learning,explainability,shap,feature importances,dash
Platform: UNKNOWN
Classifier: Development Status :: 3 - Alpha
Classifier: Environment :: Web Environment
Classifier: Framework :: Dash
Classifier: Framework :: Flask
Classifier: Intended Audience :: Developers
Classifier: Intended Audience :: Education
Classifier: Topic :: Scientific/Engineering :: Artificial Intelligence
Requires-Python: >=3.6
